{
  "timestamp": "2025-11-06T23:10:11",
  "url": "https://www.fr.de/panorama/",
  "response": {
    "status": 200
  },
  "scripts": [
    {
      "type": null,
      "src": "https://www.fr.de/fdn/bootstrap/",
      "id": null,
      "text": null
    },
    {
      "type": "module",
      "src": "https://cl.k5a.io/614855c8e16cdd72901684f2.module.js",
      "id": null,
      "text": null
    },
    {
      "type": null,
      "src": "https://cl.k5a.io/614855c8e16cdd72901684f2.nomodule.js",
      "id": null,
      "text": null
    },
    {
      "type": "text/javascript",
      "src": "https://cdn.opencmp.net/tcf-v2/cmp-stub-latest.js",
      "id": "open-cmp-stub",
      "text": null
    },
    {
      "type": "text/javascript",
      "src": "https://cdntrf.com/trfAdSetup.js",
      "id": "trfAdSetup",
      "text": null
    },
    {
      "type": "text/plain",
      "src": "https://www.fr.de/static/external/idbraze/id.braze.min.js?v=594",
      "id": "idBrazeSetup",
      "text": null
    },
    {
      "type": "text/javascript",
      "src": "https://widgets.outbrain.com/outbrain.js",
      "id": null,
      "text": null
    },
    {
      "type": "text/javascript",
      "src": "https://www.fr.de/sso/static/login/common/js/id-userid-sso.min-b4507d5454ff8246c750596bcb0298e6.js",
      "id": "iduidjs-ssowidget",
      "text": null
    },
    {
      "type": "text/plain",
      "src": "https://static.cleverpush.com/channel/loader/4Dc5cYweSTjQ74PY5.js",
      "id": null,
      "text": null
    }
  ],
  "articles": [
    {
      "title": "Auf dem Sarg: Mutter nimmt mit bewegenden Worten Abschied von getötetem Fabian",
      "teaser": "Trikot und Rad in Trauerhalle",
      "url": "https://www.fr.de/panorama/gleicht-nadel-im-heuhaufen-vermisster-achtjaehriger-verzweifelte-suche-nach-fabian-zr-93984540.html",
      "image_url": "https://www.fr.de/bilder/2025/11/06/94025760/40349762-stofftiere-und-trauer-botschaft-polizeiwagen-stehen-nebeneinander-1ihUzsYbQDRG.jpg",
      "image_title": "Auf dem Sarg: Mutter nimmt mit bewegenden Worten Abschied von getötetem Fabian"
    },
    {
      "title": "Nächster Teil der Actionspielreihe „GTA“ kommt noch später",
      "teaser": "Populäres Videospiel",
      "url": "https://www.fr.de/panorama/naechster-teil-der-actionspielreihe-gta-kommt-noch-spaeter-zr-94025784.html",
      "image_url": "https://www.fr.de/bilder/2025/11/06/94025784/40360578-grand-theft-auto-vi-2fVI.jpg",
      "image_title": "Nächster Teil der Actionspielreihe „GTA“ kommt noch später"
    },
    {
      "title": "Musk bekommt Chance auf Tesla-Aktien im Billionenwert",
      "teaser": "Mehr Aktien für Musk?",
      "url": "https://www.fr.de/panorama/musk-bekommt-chance-auf-tesla-aktien-im-billionenwert-zr-94025768.html",
      "image_url": "https://www.fr.de/bilder/2025/11/06/94025768/40360551-elon-musk-3HPI.jpg",
      "image_title": "Musk bekommt Chance auf Tesla-Aktien im Billionenwert"
    },
    {
      "title": "Ein Tag im November entscheidet über Winterwetter: Greift die Bauernregel für …",
      "teaser": "Schnee-Prognose für Süden",
      "url": "https://www.fr.de/panorama/ein-tag-im-november-entscheidet-ueber-winterwetter-greift-die-bauernregel-fuer-deutschland-94025623.html",
      "image_url": "https://www.fr.de/bilder/2025/11/06/94025623/40353048-schneefigur-auf-stein-menschen-kaempfen-mit-regenschirm-gegen-wind-3OlgveQvzla7.jpg",
      "image_title": "Ein Tag im November entscheidet über Winterwetter: Greift die Bauernregel für Deutschland?"
    },
    {
      "title": "„Ein Kind zu haben, ist pures Comedygold“",
      "teaser": "Carolin Kebekus",
      "url": "https://www.fr.de/panorama/carolin-kebekus-bricht-mit-erwartungen-an-muetter-in-neuem-buch-94024713.html",
      "image_url": "https://www.fr.de/bilder/2025/11/06/94024713/40338044-portraet-der-komikerin-carolin-kebekus-2qRzCgPOe7a7.jpg",
      "image_title": "„Ein Kind zu haben, ist pures Comedygold“"
    },
    {
      "title": "Richter billigt Boeing-Deal mit Washington zu Max-Abstürzen",
      "teaser": "737-Max-Abstürze",
      "url": "https://www.fr.de/panorama/richter-billigt-boeing-deal-mit-washington-zu-max-abstuerzen-zr-94025326.html",
      "image_url": "https://www.fr.de/bilder/2025/11/06/94025326/40358401-boeing-1MSG.jpg",
      "image_title": "Richter billigt Boeing-Deal mit Washington zu Max-Abstürzen"
    },
    {
      "title": "Mord an Fabian: Ex-Freundin des Vaters gerät in Fokus der Familie – Angehörige sieht …",
      "teaser": "Ermittlungen laufen",
      "url": "https://www.fr.de/panorama/gleicht-nadel-im-heuhaufen-vermisster-achtjaehriger-verzweifelte-suche-nach-fabian-zr-93984540.html",
      "image_url": "https://www.fr.de/bilder/2025/11/06/94025017/40352558-collage-aus-polizeibilder-aus-guestrow-und-anteilnahme-der-bevoelkerung-1Ta7.jpg",
      "image_title": "Mord an Fabian: Ex-Freundin des Vaters gerät in Fokus der Familie – Angehörige sieht „zu viele Zufälle“"
    },
    {
      "title": "Wut auf Gen-Z – aber Maschmeyer zielt auf Boomer und Millennials: „Ich kann es nicht …",
      "teaser": "Generationenunterschiede",
      "url": "https://www.fr.de/panorama/von-einer-ki-ersetzt-wirst-so-sehen-11-jobs-aus-in-denen-du-zr-93107926.html",
      "image_url": "https://www.fr.de/bilder/2025/11/05/94024853/40342551-carsten-maschmeyer-auf-dem-ludwig-erhard-gipfel-2025-auf-gut-kaltenbrunn-am-tegernsee-1YgAdaEj3Ma7.jpg",
      "image_title": "Wut auf Gen-Z – aber Maschmeyer zielt auf Boomer und Millennials: „Ich kann es nicht mehr ertragen“"
    },
    {
      "title": "Getöteter Fabian (8): Nach Ermittler-Hinweis im ZDF – großer Knall folgt am Morgen …",
      "teaser": "Bei „Aktenzeichen XY“",
      "url": "https://www.fr.de/panorama/gleicht-nadel-im-heuhaufen-vermisster-achtjaehriger-verzweifelte-suche-nach-fabian-zr-93984540.html",
      "image_url": "https://www.fr.de/bilder/2025/11/06/94024667/40353237-ermittler-frank-focke-in-der-zdf-sendung-aktenzeichen-xy-3cSG.jpg",
      "image_title": "Getöteter Fabian (8): Nach Ermittler-Hinweis im ZDF – großer Knall folgt am Morgen danach"
    },
    {
      "title": "Mann aus Bayern veränderte die Geschichte des Glühweins",
      "teaser": "Geldstrafe für „Gesetzesverstoß“",
      "url": "https://www.fr.de/panorama/gluehwein-weihnachtsmarkt-christkindlesmarkt-weihnachten-bayern-getraenk-wein-zr-91932342.html",
      "image_url": "https://www.fr.de/bilder/2022/11/21/91932342/40303981-christmas-holiday-hot-drink-mulled-wine-in-glasses-on-wooden-table-1ya7.jpg",
      "image_title": "Mann aus Bayern veränderte die Geschichte des Glühweins"
    },
    {
      "title": "Neue Entwicklung im Fall Fabian (8): „Haftbefehl gegen eine weibliche Person“",
      "teaser": "Nach Ausstrahlung von ZDF-Sendung",
      "url": "https://www.fr.de/panorama/gleicht-nadel-im-heuhaufen-vermisster-achtjaehriger-verzweifelte-suche-nach-fabian-zr-93984540.html",
      "image_url": "https://www.fr.de/bilder/2025/11/06/94025718/40355976-auf-der-rechten-seite-der-getoetete-fabian-aus-guestrow-links-mehrere-polizisten-bei-einer-hausdurchsuchung-3Ka7.jpg",
      "image_title": "Neue Entwicklung im Fall Fabian (8): „Haftbefehl gegen eine weibliche Person“"
    },
    {
      "title": "Rotgoldene Bäume, mystische Nebelschwaden: So schön zeigt sich der Herbst in Bayern",
      "teaser": "Herbststimmung in Bildern",
      "url": "https://www.fr.de/panorama/rotgoldene-baeume-mystische-nebelschwaden-so-schoen-zeigt-sich-der-herbst-in-bayern-zr-94025689.html",
      "image_url": "https://www.fr.de/bilder/2025/11/04/94025689/40329513-herbst-in-bayern-La7.jpg",
      "image_title": "Rotgoldene Bäume, mystische Nebelschwaden: So schön zeigt sich der Herbst in Bayern"
    },
    {
      "title": "22 Erziehungsfehler, die Eltern bei ihren Kindern vermeiden sollten",
      "teaser": "Familie",
      "url": "https://www.fr.de/panorama/22-erziehungsfehler-die-eltern-bei-ihren-kindern-vermeiden-sollten-zr-94005495.html",
      "image_url": "https://www.fr.de/bilder/2025/10/23/94005495/40184948-maedchen-auf-sofa-traurig-1NQI.jpg",
      "image_title": "22 Erziehungsfehler, die Eltern bei ihren Kindern vermeiden sollten"
    },
    {
      "title": "Verheerende Unwetter in Mexiko: Bilder zeigen Spur der Verwüstung",
      "teaser": "260 Ortschaften isoliert",
      "url": "https://www.fr.de/panorama/verheerende-unwetter-in-mexiko-bilder-zeigen-spur-der-verwuestung-zr-93983363.html",
      "image_url": "https://www.fr.de/bilder/2025/10/13/93983363/40053317-schwere-unwetter-haben-in-mexiko-eine-spur-der-verwuestung-hinterlassen-2pFTeML5juQI.jpg",
      "image_title": "Verheerende Unwetter in Mexiko: Bilder zeigen Spur der Verwüstung"
    }
  ]
}