{
  "timestamp": "2025-08-19T08:14:05",
  "url": "https://www.volksstimme.de/",
  "response": {
    "status": 200
  },
  "scripts": [
    {
      "type": "text/javascript",
      "src": "https://data-11c63b1cbc.volksstimme.de/iomm/latest/bootstrap/loader.js",
      "id": null,
      "text": null
    },
    {
      "type": null,
      "src": "https://applets.ebxcdn.com/ebx.js",
      "id": "ebx",
      "text": null
    },
    {
      "type": null,
      "src": "https://www.volksstimme.de/static/scripts/scripts.e3cb9d79.js",
      "id": null,
      "text": null
    },
    {
      "type": null,
      "src": "https://www.volksstimme.de/static/scripts/adScripts.e3cb9d79.js",
      "id": null,
      "text": null
    },
    {
      "type": null,
      "src": "https://static.dumontnext.de/revenue/lightworks-vs.js",
      "id": null,
      "text": null
    },
    {
      "type": null,
      "src": "https://cdn.dl.volksstimme.de/bineosmgm/content/Bineos_2_0/bineos.min.js",
      "id": null,
      "text": null
    },
    {
      "type": null,
      "src": "https://static.cloudflareinsights.com/beacon.min.js/vcd15cbe7772f49c399c6a5babf22c1241717689176015",
      "id": null,
      "text": null
    }
  ],
  "articles": [
    {
      "title": "60-jähriger Mann in Magdeburg brutal mit Metallstange attackiert",
      "image_url": "https://bmg-images.forward-publishing.io/2025/08/13/3024de9f-1d95-44b1-ba94-f6c952da4cf1.jpeg?rect=125%2C169%2C1797%2C1011&width=100",
      "image_title": "Ein 60-Jähriger ist am Freitag in Magdeburg attackiert worden.",
      "topic": "Täter gefasst"
    },
    {
      "title": "Fleisch nicht mehr so gefragt: Nächste Pleite droht in Salzwedel",
      "image_url": "https://bmg-images.forward-publishing.io/2025/08/18/b8e9bd27-d74d-476a-b6f1-6019c4235742.jpeg?rect=0%2C177%2C1666%2C937&width=100",
      "image_title": "Von der Schließung bedroht: die Dehning-Filiale im Kaufland Salzwedel.",
      "topic": "Wirtschaft"
    },
    {
      "title": "AfD will Burkini in Magdeburg verbieten – Stadträte reagieren empört",
      "image_url": "https://bmg-images.forward-publishing.io/2025/08/18/ca1ddfa7-f54e-4245-bc21-e125015429c2.jpeg?rect=417%2C0%2C3115%2C1753&width=100",
      "image_title": "Bikini oder Burkini? Wer entscheidet wie viel Haut eine Frau im Schwimmbad zeigen soll? In Magdeburg will die AfD den Burkini verbieten.",
      "topic": "Sorge oder Symbolpolitik?"
    },
    {
      "title": "„Es wird nie wieder, wie es mal war“: Ausgehen am Magdeburger Hassel",
      "url": "https://www.volksstimme.de/lokal/magdeburg/hasselbachplatz-hassel-kneipensterben-cafe-bar-polizei-4100141",
      "image_url": "https://bmg-images.forward-publishing.io/2025/08/18/2c0a91cb-0fc1-4f95-969e-8fc0e28487a5.jpeg?rect=146%2C213%2C1400%2C787&width=100",
      "image_title": "Zu Veranstaltungen wie „Hassel Fever“ oder „Macht der Nacht“ kamen früher Tausende zum Magdeburger Hasselbachplatz.",
      "topic": "Anlieger sprechen über Kneipenviertel"
    },
    {
      "title": "Krabbelgruppe-Wut, Mauschel-Vorwürfe und eine Entschuldigung - so wehrt sich OB Borris",
      "url": "https://www.volksstimme.de/lokal/magdeburg/krabbelgruppe-wut-mauschel-vorwurfe-und-eine-entschuldigung-so-wehrt-sich-ob-borris-4099962",
      "image_url": "https://bmg-images.forward-publishing.io/2025/08/18/2d983c06-ce4c-4e49-b8d6-098a931af074.jpeg?rect=12%2C245%2C3744%2C2240&width=100",
      "image_title": "Magdeburgs OB Simone Borris geht auf die Vorwürfe in einer Erklärung ein.",
      "topic": "Weihnachtsmarkt-Affäre Magdeburg"
    },
    {
      "title": "Magdeburger Schausteller in Not: „Da stecken Mitarbeiter und Familien hinter“",
      "url": "https://www.volksstimme.de/lokal/magdeburg/schausteller-weihnachtsmarkt-umsatzausfaelle-not-mitarbeiter-4100131",
      "image_url": "https://bmg-images.forward-publishing.io/2025/08/18/23995654-b435-442f-aba9-382ec405c9a0.jpeg?rect=0%2C282%2C4000%2C2250&width=100",
      "image_title": "Krisentreffen von Schaustellern des Magdeburger Weihnachtsmarktes: Nico Barth (v.l.), Ralf Haase, Werner Jacob und Gunther Boos machen sich Sorgen um die Qualität des Budenzaubers.",
      "topic": "Enorme Umsatzausfälle nach Weihnachtsmarkt-Anschlag"
    },
    {
      "title": "Die neue App der Volksstimme: Alle Ihre Vorteile auf einem Blick - Jetzt kostenlos downloaden!",
      "url": "https://www.volksstimme.de/service/in-eigener-sache/e-paper-und-live-news-die-neue-app-der-volksstimme-ihre-vorteile-auf-einem-blick-3879758",
      "image_url": "https://bmg-images.forward-publishing.io/2024/07/11/99825264-721c-4bab-bf03-ad6e812a5a2c.jpeg?rect=0%2C0%2C3307%2C1860&width=100",
      "image_title": "Die neue App der Volksstimme bietet viele Vorteile für Leser.",
      "topic": "E-PAPER UND LIVE-NEWS zusammen"
    },
    {
      "title": "Foto-Aktion \"Sommer, Sonne, Sachsen-Anhalt\": Welches Sommerfoto finden Sie am schönsten?",
      "url": "https://www.volksstimme.de/service/sommer-fotoaktion-sachsen-anhalt-4029717",
      "image_url": "https://bmg-images.forward-publishing.io/2025/05/27/7cb1bb8e-17e9-4f6e-ba28-8d5655dd691c.jpeg?rect=0%2C121%2C2886%2C1623&width=100",
      "image_title": "Wir suchen das schönste Sommerfoto Sachsen-Anhalts:",
      "topic": "Jetzt Abstimmen!"
    },
    {
      "title": "Germania Halberstadt gewinnt gegen VfB Auerbach - die Highlights und das Spiel in voller Länge!",
      "url": "https://www.volksstimme.de/live/live-stream-germania-halberstadt-vfb-auerbach-nofv-oberliga-4089892",
      "image_url": "https://bmg-images.forward-publishing.io/2025/07/29/6a3173af-85f7-4e0d-ba1c-9aec6a0dffb8.jpeg?rect=0%2C1%2C3508%2C1973&width=100",
      "image_title": "Am 10. August spielen VfB Germania Halberstadt und VfB Auerbach in der NOFV-Oberliga gegeneinander. Volksstimme und Mitteldeutsche Zeotung zeigen die Partie im Livestream.",
      "topic": "NOFV-Oberliga am 10. August"
    },
    {
      "title": "Mit Video: Nach Eröffnung - dieser Trendsport begeistert in Magdeburg",
      "url": "https://www.volksstimme.de/lokal/magdeburg/padel-trend-sport-magdeburg-4095137",
      "image_url": "https://bmg-images.forward-publishing.io/2025/08/11/c8940f05-f698-42fa-92eb-fb93ea0e9baf.jpeg?rect=0%2C0%2C1600%2C900&width=100",
      "image_title": "Matias Tosi (rechts) spielt seit seiner Kindheit Padel. In Magdeburg eröffnete er 2024 eine eigene Padel-Anlage, die er mit Unterstützung von Jörg Gaßdorf betreibt.",
      "topic": "Hype um neue Sportart"
    },
    {
      "title": "Mit Video: Geheimnisvolle Pakete in Stendal - Lohnt sich der Kauf?",
      "url": "https://www.volksstimme.de/lokal/stendal/secret-packs-stendal-kauf-video-4095310",
      "image_url": "https://bmg-images.forward-publishing.io/2025/08/08/ed40a3bc-86f7-4852-8a59-c8c3c97b6e76.jpeg?rect=0%2C0%2C1600%2C900&width=100",
      "image_title": "Jens und Jessica Braunschweig bieten in den Aral-Tankstellen in Stendal „Secret Packs“ zum Verkauf an. Was man bekommt, bleibt bis zum Schluss eine Überraschung.",
      "topic": "Volksstimme testet"
    },
    {
      "title": "Mit Video: Amoklagen, Terror und Anschläge - Für Polizisten entscheiden Sekunden über Leben und Tod",
      "url": "https://www.volksstimme.de/sachsen-anhalt/amok-terror-anschlag-gefahr-polizei-training-aschersleben-4094742",
      "image_url": "https://bmg-images.forward-publishing.io/2025/08/08/6b45a0d7-3f8c-4c8c-8aaf-f2b35cc19c17.jpeg?rect=0%2C12%2C1600%2C877&width=100",
      "image_title": "Die Polizisten pirschen sich mit der Maschinenpistole im Anschlag an die Situation heran. Auf dem Gelände eines ehemaligen Institutes für Gartenbau gab es Schüsse.",
      "topic": "Schüsse in Aschersleben"
    },
    {
      "title": "Mit Video: Behelfsbrücken am Damaschkeplatz in Magdeburg für Verkehr freigegeben",
      "url": "https://www.volksstimme.de/lokal/magdeburg/bruecke-baustelle-damaschkeplatz-umleitung-verkehr-4095201",
      "image_url": "https://bmg-images.forward-publishing.io/2025/08/08/54074d99-e76a-49ce-81b5-7593255d1dd8.jpeg?rect=0%2C0%2C1600%2C900&width=100",
      "image_title": "Am Freitag gab die Stadt Magdeburg die Behelfsbrücken am Damaschkeplatz für den Verkehr frei. Damit reagiert die Stadt auf die Sperrung der Ringbrücken über der Halberstädter Straße und der Brenneckestraße.",
      "topic": "Nach weiteren Brückensperrungen"
    },
    {
      "title": "Immobilien-Experte blickt für Magdeburg so in die Zukunft",
      "url": "https://www.volksstimme.de/lokal/magdeburg/immobilien-experte-blickt-fur-magdeburg-so-in-die-zukunft-4100133",
      "image_url": "https://bmg-images.forward-publishing.io/2025/08/18/52be0beb-a48c-4a8c-9826-d2d41f70af2e.jpeg?rect=0%2C0%2C2361%2C1494&width=100",
      "image_title": "Intel hat sich getrennt - von der Investition in Magdeburg.",
      "topic": "Nach Intel-Rückzug in Sachsen-Anhalt"
    },
    {
      "title": "Wildpinkeln, lautes Brummen und Mülltüten - Jütrichauer fordern: Es muss was passieren",
      "url": "https://www.volksstimme.de/lokal/zerbst/wildpinkeln-lautes-brummen-und-mulltuten-jutrichauer-fordern-es-muss-was-passieren-4100157",
      "image_url": "https://bmg-images.forward-publishing.io/2025/08/18/657fe935-2f4d-4f43-a014-ddf6248f1c0d.jpeg?rect=0%2C418%2C840%2C472&width=100",
      "image_title": "Die Parkplätze sind nur für Pkw vorgesehen.",
      "topic": "LKW-Fahrer benehmen sich daneben"
    },
    {
      "title": "Café Kurt in Magdeburg wird zum Kiezcafé Pipper: Was die neue Betreiberin plant",
      "url": "https://www.volksstimme.de/lokal/magdeburg/cafe-kurt-kiezcafe-pipper-betreiberwechsel-eroeffnung-oeffnungszeiten-4100140",
      "image_url": "https://bmg-images.forward-publishing.io/2025/08/18/868c64b9-902c-4d31-b60c-3725a2c11098.jpeg?rect=0%2C381%2C4000%2C2250&width=100",
      "image_title": "Das Café Kurt in Magdeburg-Buckau schließt. Unter dem Namen „Pipper Kiezcafé\" eröffnet Saskia Amend den Laden einige Wochen später wieder.",
      "topic": "Kaffee, Kuchen und Kunst"
    },
    {
      "title": "„Zu wenig Leute da im Amt“: Möckern verliert den Kampf gegen den Dreck",
      "url": "https://www.volksstimme.de/lokal/burg/zu-wenig-leute-da-im-amt-mockern-verliert-den-kampf-gegen-den-dreck-4100091",
      "image_url": "https://bmg-images.forward-publishing.io/2025/08/18/cb6ba247-58b1-4006-8354-88a4a5e9b43d.jpeg?rect=17%2C0%2C1248%2C967&width=100",
      "image_title": "Die Mitarbeiter des Ordnungsamtes Möckern sollen theoretisch auch kontrollieren, ob die über 13.000 Möckeraner in den auf 524 Quadratkilometern verteilten 50 Ortsteilen ihrer Straßenreinigungspflicht nachkommen.",
      "topic": "Trotz andauernder Beschwerden"
    },
    {
      "title": "Pommes selbst geschnitten: Wie ein neuer Imbiss in Arendsee Kunden locken soll",
      "url": "https://www.volksstimme.de/lokal/arendsee/pommes-selbst-geschnitten-wie-ein-neuer-imbiss-in-arendsee-kunden-locken-soll-4100384",
      "image_url": "https://bmg-images.forward-publishing.io/2025/08/19/52af25b4-a9d5-4bee-8e93-d7c00bfc8a43.jpeg?rect=0%2C160%2C1365%2C676&width=100",
      "image_title": "Salatteller und Hamburger: Bärbel Rammler zeigt eine Auswahl.",
      "topic": "Mehr Angebote vor dem Rathaus"
    },
    {
      "title": "Traurige Nachricht überschattet 44. Halberstädter Tiergartenfest",
      "url": "https://www.volksstimme.de/lokal/halberstadt/halberstadt-tiergartenfest-familienevent-harz-todesfall-vergiftung-tierwohl-4099712",
      "image_url": "https://bmg-images.forward-publishing.io/2025/08/17/176785fe-67a2-47e1-ac85-7d90e0c40274.jpeg?rect=340%2C492%2C3240%2C1821&width=100",
      "image_title": "Füttern unter Aufsicht erlaubt war an einigen Gehegen des Halberstädter Tiergartens bei den Showfütterungen zum diesjährigen Tiergartenfest am 17. August.",
      "topic": "Familientag in Halberstadts Spiegelsbergen"
    },
    {
      "title": "XXL-Krakauer und Burger: Neues Imbiss-Highlight in Burg eröffnet",
      "url": "https://www.volksstimme.de/lokal/burg/xxl-krakauer-und-burger-neues-imbiss-highlight-in-burg-eroffnet-4100138",
      "image_url": "https://bmg-images.forward-publishing.io/2025/08/18/8b847726-f4ac-44a9-a186-4294bdd68abb.jpeg?rect=308%2C239%2C3336%2C1877&width=100",
      "image_title": "Der frisch eröffnete Imbiss an der Total-Tankstelle in Burg: Lucas Rehfeld (links) und Matthias Güttler (rechts) freuen sich auf alle, die beim Tanken doch nochmal der Hunger packt.",
      "topic": "Zur Eröffnung gibt’s etwas kostenlos"
    },
    {
      "title": "Spektakuläre Bohrungen für Wernigerodes Ortsumfahrung: Wie sicher ist der Untergrund für den Mega-Tunnel?",
      "url": "https://www.volksstimme.de/lokal/wernigerode/spektakulare-bohrungen-fur-wernigerodes-ortsumfahrung-wie-sicher-ist-der-untergrund-fur-den-mega-tunnel-4099885",
      "image_url": "https://bmg-images.forward-publishing.io/2025/08/18/4a4d6e40-d7c4-4bb8-96c9-f45f65c18289.jpeg?rect=0%2C0%2C3990%2C2992&width=100",
      "image_title": "Der Schwerlastverkehr auf der B244 sorgt in Wernigerode für Lärm, Dreck und Kritik. Die geplante Ortsumfahrung soll das Problem lösen.",
      "topic": "Trasse für 160 Millionen Euro"
    },
    {
      "title": "Wie ein Magdeburger Verein seine Kultkneipe vor dem Aus rettete – und sie jetzt beliebter ist denn je",
      "url": "https://www.volksstimme.de/lokal/magdeburg/kleingartenverein-dach-sanierung-kneipe-4099713",
      "image_url": "https://bmg-images.forward-publishing.io/2025/08/17/0f64ae38-eea5-47b8-b64a-6266457f992e.jpeg?rect=0%2C0%2C4000%2C3000&width=100",
      "image_title": "Gerd Albrecht (links) und Ingolf Neumann, Vereinsvorsitzender der vom Kleingartenverein „Vogelsang“ im Versammlungssaal der „Vogelpiepe“. Nachdem der Dachstuhl neu gemacht wurde, kann die Kultkneipe wieder vermietet werden.",
      "topic": "„Vogelpiepe“ bis 2028 gebucht"
    },
    {
      "title": "Mit dem E-Scooter durch Magdeburg: So funktioniert es",
      "url": "https://www.volksstimme.de/lokal/magdeburg/e-scooter-e-mobilitaet-regeln-kosten-voi-4099477",
      "image_url": "https://bmg-images.forward-publishing.io/2025/08/17/e9ac8421-2750-4ed4-bf3e-ab21281560cf.jpeg?rect=0%2C0%2C4000%2C3000&width=100",
      "image_title": "Wer in Magdeburg einen E-Scooter ausleihen möchte, muss einige Regeln beachten.",
      "topic": "Verleih neu geregelt"
    },
    {
      "title": "Theaterfestival „Salzwedeler Kulturnächte“ feiert Premiere",
      "url": "https://www.volksstimme.de/lokal/salzwedel/theaterfestival-salzwedeler-kulturnachte-feiert-premiere-4100448",
      "image_url": "https://bmg-images.forward-publishing.io/2025/08/19/82021dc6-f6a2-4270-8a8e-f451072440d0.jpeg?rect=0%2C83%2C1969%2C1108&width=100",
      "image_title": "Moby Dick Aufführung der Freien Bühne Wendland - hier in Wismar 2022.",
      "topic": "Kultur"
    },
    {
      "title": "Naturschützer kritisieren Abschuss-Freigabe",
      "url": "https://www.volksstimme.de/lokal/oebisfelde/wolf-abschuss-niedersachsen-kritik-4100168",
      "image_url": "https://bmg-images.forward-publishing.io/2025/08/18/fc3ea6d1-7231-4772-8598-5b9e39f313f9.jpeg?rect=0%2C95%2C1895%2C1066&width=100",
      "image_title": "Das Land Niedersachsen hat einen Wolf zum Abschuss freigegeben, der auch im Bereich Walbeck Damwild in einem Gehege gerissen haben soll. Noch ist das Tier allerdings nicht erlegt.",
      "topic": "Problemwolf im Drömling"
    },
    {
      "title": "Calbe: Von wegen jung und faul",
      "url": "https://www.volksstimme.de/lokal/schoenebeck/calbe-von-wegen-jung-und-faul-4099915",
      "image_url": "https://bmg-images.forward-publishing.io/2025/08/18/dd6e2437-c299-4658-9705-68a149237880.jpeg?rect=0%2C234%2C3190%2C1597&width=100",
      "image_title": "Lars Wohlfahrt macht hier beim Schulfest Musik und heizt den Schülern noch mehr ein.",
      "topic": "Schüler packen an"
    },
    {
      "title": "Nach elf Jahren ist Schluss: Kirchengemeinde verabschiedet Haldensleber Pfarrer",
      "url": "https://www.volksstimme.de/lokal/haldensleben/nach-elf-jahren-ist-schluss-kirchengemeinde-verabschiedet-haldensleber-pfarrer-4100147",
      "image_url": "https://bmg-images.forward-publishing.io/2025/08/18/6b7bdc0a-e62b-4de7-b66f-fb2ab4083051.jpeg?rect=115%2C0%2C1511%2C850&width=100",
      "image_title": "Superintendent Uwe Jauch (r.) spricht Pfarrer Matthias Simon neben Gemeindepädagoge Robert Neumann zum Abschied seinen Segen aus.",
      "topic": "Evangelische Kirchengemeinde St. Marien"
    },
    {
      "title": "Große Feier im kleinen Ort: Was Hakeborner und ihre Gäste beim Familienfest erleben",
      "url": "https://www.volksstimme.de/lokal/stassfurt/grosse-feier-im-kleinen-ort-was-hakeborner-und-ihre-gaste-beim-familienfest-erleben-4100196",
      "image_url": "https://bmg-images.forward-publishing.io/2025/08/18/9584a342-a1d2-48be-92c0-9962ad207b51.jpeg?rect=5%2C246%2C2656%2C1493&width=100",
      "image_title": "Beim Kinder- und Familiensportfest des SV „Warthe“ Hakeborn kamen auch die kleinsten Gäste nicht zu kurz. Sie konnten dort unter alten Bäumen malen oder sich tätowieren lassen. Vereinschef Nils Heinemann (r.) und Gemeinderat Benjamin Seilz schauten ihnen dabei über die Schulter.",
      "topic": "Sportverein organisiert Fest"
    },
    {
      "title": "Eine Tankstelle für Bobbycars: Engagierter Vater lässt Kindertraum im Harz wahr werden",
      "url": "https://www.volksstimme.de/lokal/blankenburg/eine-tankstelle-fur-bobbycars-engagierter-vater-lasst-kindertraum-im-harz-wahr-werden-4100286",
      "image_url": "https://bmg-images.forward-publishing.io/2025/08/18/090d1dea-d7cb-4886-94eb-81d55119bb68.jpeg?rect=0%2C525%2C4000%2C2250&width=100",
      "image_title": "Die drei von der Tankstelle: Erbauer Marco Gadegast, seine Frau Sarah (links) und Kita-Chefin Nancy Müller (Mitte).",
      "topic": "Überraschung in Timmenrode"
    },
    {
      "title": "Hohe Geldstrafe fürs Radfahren mit 2,66 Promille",
      "url": "https://www.volksstimme.de/lokal/salzwedel/hohe-geldstrafe-furs-radfahren-mit-2-66-promille-4100431",
      "image_url": "https://bmg-images.forward-publishing.io/2025/08/19/bba7c978-861b-4237-af4d-ed0a66482351.jpeg?rect=0%2C0%2C1752%2C1446&width=100",
      "image_title": "Ein Radfahrer trinkt aus einer Bierflasche: Fahrradfahren in betrunkenem Zustand ist eine Straftat und kann sehr teuer werden.",
      "topic": "Betrunken im Straßenverkehr"
    },
    {
      "title": "Verkehrsbehinderungen und Stau möglich: Gemeinde ruft zur großen Demo auf",
      "url": "https://www.volksstimme.de/lokal/wolmirstedt/verkehrbehinderungen-und-stau-moglich-gemeinde-ruft-zur-grossen-demo-auf-4100401",
      "image_url": "https://bmg-images.forward-publishing.io/2025/08/19/7ea1f075-28e0-4950-89d5-55028afe733e.jpeg?rect=0%2C153%2C1503%2C845&width=100",
      "image_title": "Nichts ging mehr für Autos: Die Kreuzung wurde zur Demo im verganbgenen Jahr von der Polizei für zehn Minuten komplett gesperrt.",
      "topic": "Forderung nach mehr Radwegen"
    },
    {
      "title": "Das ist der Dienstag im Salzlandkreis",
      "url": "https://www.volksstimme.de/lokal/schoenebeck/slk-live-der-newsblog-das-ist-der-dienstag-im-salzlandkreis-4100139",
      "image_url": "https://bmg-images.forward-publishing.io/2024/03/11/1c2f5c07-3450-4f4b-89dd-c4839293e930.jpeg?rect=20%2C31%2C1099%2C618&width=100",
      "image_title": "Alles, was im Salzlandkreis wichtig ist, erfahren Sie den ganzen Tag über bei SLK Live.",
      "topic": "SLK live: Der Newsblog"
    },
    {
      "title": "Landkreis Stendal: Warum es neue Stärke aus der Knolle gibt",
      "url": "https://www.volksstimme.de/lokal/havelberg/landkreis-stendal-warum-es-neue-starke-aus-der-knolle-gibt-4100380",
      "image_url": "https://bmg-images.forward-publishing.io/2025/08/19/136be192-b11d-4241-9410-b19934155ae7.jpeg?rect=612%2C35%2C2346%2C1319&width=100",
      "image_title": "Landwirt Hubert Aselmeyer aus Rehberg und die Firma Köpke aus Garz ernteten erste Kartoffeln im Elb-Havel-Winkel. Für den Hof des Landwirts eine Premiere.",
      "topic": "Klimawandel und Landwirtschaft"
    },
    {
      "title": "Forest Jump, Olé-Party und viele mehr – Diese Festivals finden 2025 in Sachsen-Anhalts statt",
      "url": "https://www.volksstimme.de/sachsen-anhalt/festival-konzerte-sommer-2025-ferropolis-rock-hiphop-indie-rap-3959910",
      "image_url": "https://bmg-images.forward-publishing.io/2025/08/19/f05b315d-9d52-4ebb-8667-cd4b9995819e.jpeg?rect=0%2C0%2C4000%2C2250&width=100",
      "image_title": "Auch der Sommer 2025 wird durch zahlreiche Festivals wie „Forest Jump“ oder die „Olé-Party“ unvergesslich werden.",
      "topic": "Der Sommer wird laut und musikalisch"
    },
    {
      "title": "Wetter in Sachsen-Anhalt: Sommerliche Hitze und Sonne – Temperatursturz zum Wochenende",
      "url": "https://www.volksstimme.de/sachsen-anhalt/wetter-regen-sonne-wolken-dwd-wetterdienst-vorhersage-4004961",
      "image_url": "https://bmg-images.forward-publishing.io/2025/08/19/a05bcda6-6ee8-41ff-88ea-7a43bbbbb54f.jpeg?rect=0%2C548%2C3557%2C2001&width=100",
      "image_title": "In Sachsen-Anhalt zeigt sich der Sommer im August in seiner vollen Pracht.",
      "topic": "Kein Regen erwartet"
    },
    {
      "title": "Manch Totgesagte leben länger",
      "url": "https://www.volksstimme.de/sachsen-anhalt/manch-totgesagte-leben-langer-4100111",
      "image_url": "https://bmg-images.forward-publishing.io/2025/08/18/86df8b13-3df2-443e-81db-779092db965f.jpeg?rect=0%2C60%2C3971%2C2234&width=100",
      "image_title": "Stefan Buhtz am Tresen seiner Dahlenwarsleber Kneipe",
      "topic": "Kneipensterben in Sachsen-Anhalt"
    },
    {
      "title": "Land setzt beim Deutscherwerb für ausländische Kinder auf Externe",
      "url": "https://www.volksstimme.de/sachsen-anhalt/landespolitik/land-setzt-beim-deutscherwerb-fur-auslandische-kinder-auf-externe-4100194",
      "image_url": "https://bmg-images.forward-publishing.io/2025/08/18/334bd096-f209-4deb-9098-449790c82420.jpeg?rect=0%2C0%2C3976%2C2922&width=100",
      "image_title": "<source>Robert Michael/dpa<sha1>154l616BYe4gOdfV79hMb5guRge</sha1><p>Syrischer Bürgerkrieg, Ukraine-Krieg, Wirtschaftsmigration – internationale Krisen haben die Zusammensetzung der Schülerschaft in Sachsen-Anhalt deutlich verschoben. Knapp 23.000 Kinder und Jugendliche und <a href=\"https://www.volksstimme.de/sachsen-anhalt/landespolitik/erstmals-seit-jahren-weniger-schuler-zum-schulbeginn-in-sachsen-anhalt-4094648\">damit gut jeder zehnte der 214.000 Schüler im Land</a> hat inzwischen eine ausländische Staatsangehörigkeit, darunter allein 6.600 Ukrainer.</p><h2>Zusammenarbeit mit externen Anbietern an bis zu 24 Standorten in Sachsen-Anhalt</h2><p>Viele der Neuankömmlinge können indes <a href=\"https://www.volksstimme.de/sachsen-anhalt/landespolitik/schule-bildung-kinder-erstklaessler-sprachprobleme-4090119\">kaum oder gar kein Deutsch</a>. Das wiederum brachte bereits im vergangenen Jahr Schulen ans Limit. <a href=\"https://www.volksstimme.de/sachsen-anhalt/euro-schule-fluechtling-schueler-burgenlandkreis-kosten-deutsch-unterricht-ukraine-3780898\">Im Burgenlandkreis etwa konnten Hunderte Kinder wegen Personalnot zeitweise gar nicht unterrichtet werden</a>. Als Ausweg setzen Landkreis und Bildungsministerium auf das Engagement privater Partner wie den „Euro-Schulen“. Im neuen Schuljahr will das Land die Kooperation mit den Externen nun noch deutlich ausbauen. <a href=\"https://www.volksstimme.de/sachsen-anhalt/landespolitik/zu-viele-schuler-in-sachsen-anhalt-konnen-kaum-deutsch-3928732\">An bis zu 24 statt acht Standorten will das Land die Hilfe von Firmen oder Volkshochschulen in Anspruch nehmen</a>. Darunter sind Schulen in Magdeburg, Halle, Weißenfels, Merseburg, Naumburg und Burg – neuerdings auch in Salzwedel, Gardelegen, Stendal, Bernburg, Dessau-Roßlau oder Wittenberg. </p><h2>Land stellt 4,2 Millionen Euro aus Corona-Sondervermögen bereit</h2><p>Der Schwerpunkt liegt auf den Sekundarschulen, aber auch Grundschulen sind dabei. 1,86 Millionen Euro stellt das Land dafür aus dem Corona-Sondervermögen allein für 2025 bereit. Im kommenden Jahr sollen es weitere 2,3 Millionen Euro sein. Die Förderung soll sowohl schulintern als auch außerhalb der Schulen stattfinden, teilte das Ministerium mit. Eine ausschließlich integrative Förderung sei vor allem wegen „personeller Engpässe und hoher Belastung des Stammpersonals nicht überall tragfähig“, hieß es. Das gelte vor allem für<a href=\"https://www.volksstimme.de/lokal/burg/neue-schulbezirke-fur-grundschulen-in-burg-das-andert-sich-in-der-kreisstadt-und-niegripp-3976325\"> Schulen mit hohen Zugangszahlen, wo oft auch nicht genügend Räume vorhanden seien</a>. </p><p>Bildungsminister Jan Riedel (CDU) sagte dazu: „Das Land ist in Sachen Sprachförderung auf mehreren Wegen unterwegs.“ Damit zugewanderte Kinder und Jugendliche schnell ankommen können, setze man auf direkte Förderung im Unterricht, ergänzende Sprachkurse und die Unterstützung durch qualifizierte Lehrer. „Mit neuen Stellen, zusätzlichen Angeboten und gezielter Qualifizierung stärken wir die Schulen dort, wo die Herausforderungen am größten sind“, so der Minister. </p><h2>145 Lehrer für Deutsch als Zielsprache eingestellt</h2><p>Tatsächlich beschäftigt das Land laut Ministerium auch 145 Lehrer mit dem Fach „Deutsch als Zielsprache“ (DAZ). Zum neuen Schuljahr wurden 44 weitere DAZ-Stellen ausgeschrieben. Eine von der Nationalen Akademie der Wissenschaften (Leopoldina) publik gemachte Studie der Uni Halle stellt der gesonderten Beschulung von Zuwanderern unterdessen schlechte Noten aus:</p><div class=\"zitat\"><p class=\"zitattext\">Wir haben festgestellt, dass ehemalige Schüler von Willkommensklassen auch Jahre später noch geringere Sprachkenntnisse als jene Flüchtlinge haben, die von Anfang an Regelklassen besuchten.</p><p class=\"zitatautor\">Oliver Winkler, Institut für Soziologie der Universität Halle</p></div><p>„Wir haben festgestellt, dass ehemalige Schülerinnen und Schüler von Willkommensklassen auch Jahre später noch geringere Sprachkenntnisse als jene Flüchtlinge haben, die von Anfang an Regelklassen besuchten“, sagte Oliver Winkler vom Institut für Soziologie der Universität. In Vorbereitungsklassen gelinge es offenbar nicht ausreichend, Anfangsunterschiede beim Sprachniveau auszugleichen. </p><p>Als Grund vermuten die Studienautoren den mangelnden Kontakt zu deutschen Schülern. Befragt wurden mehr als 1.097 Jugendliche aus Bayern, Sachsen, Rheinland-Pfalz und Nordrhein-Westfalen. Die Lehrergewerkschaft GEW bewertet das ähnlich: „Schulen mit Personalproblemen extern zu unterstützen ist keine schlechte Lösung“, sagte Landeschefin Eva Gerth. „Wichtig ist aber, dass die Förderung – wenn möglich – in der Schule erfolgt.“ Hier finde der Kontakt zu deutschen Mitschülern statt.</p>",
      "topic": "Sprachoffensive für Sachsen-Anhalts Schulen"
    },
    {
      "title": "Wer kauft das Intel-Gelände bei Magdeburg?",
      "url": "https://www.volksstimme.de/sachsen-anhalt/wer-kauft-das-intel-gelande-bei-magdeburg-4100187",
      "image_url": "https://bmg-images.forward-publishing.io/2025/08/18/452e99ef-c0ff-40ee-891d-e62d666b055b.jpeg?rect=0%2C0%2C4000%2C2250&width=100",
      "image_title": "Blick auf die Felder, auf denen der US-amerikanische Technologie-Konzern Intel eine Chipfabrik bauen wollte.",
      "topic": "Landtag Sachsen-Anhaltdebattiert über Optionen"
    },
    {
      "title": "Dicke Briefe: Das müssen Sparkassenkunden in der Börde jetzt wissen",
      "url": "https://www.volksstimme.de/lokal/wolmirstedt/sparkasse-konto-echtzeitueberweisung-vertrag-zustimmung-4098996",
      "topic": "Nach Gerichtsurteil neue Regeln"
    },
    {
      "title": "Traurige Nachricht überschattet 44. Halberstädter Tiergartenfest",
      "url": "https://www.volksstimme.de/lokal/halberstadt/halberstadt-tiergartenfest-familienevent-harz-todesfall-vergiftung-tierwohl-4099712",
      "topic": "Familientag in Halberstadts Spiegelsbergen"
    },
    {
      "title": "Riesige Rauchsäule: Auf dem Truppenübungsplatz Altmark brennt es",
      "url": "https://www.volksstimme.de/lokal/gardelegen/riesige-rauchsaule-auf-dem-truppenubungsplatz-altmark-brennt-es-4100118",
      "topic": "Gardelegener beunruhigt"
    },
    {
      "title": "Krabbelgruppe-Wut, Mauschel-Vorwürfe und eine Entschuldigung - so wehrt sich OB Borris",
      "url": "https://www.volksstimme.de/lokal/magdeburg/krabbelgruppe-wut-mauschel-vorwurfe-und-eine-entschuldigung-so-wehrt-sich-ob-borris-4099962",
      "topic": "Weihnachtsmarkt-Affäre Magdeburg"
    },
    {
      "title": "Stefanie Hertel rockt den Bierer Berg in Schönebeck",
      "url": "https://www.volksstimme.de/lokal/schoenebeck/stefanie-hertel-schlager-bierer-berg-fest-4099662",
      "topic": "Schlager-Party Open Air"
    },
    {
      "title": "ABC-Alarm: Feuerwehreinsatz in Wohnpark in Stendal",
      "url": "https://www.volksstimme.de/blaulicht/stendal/abc-alarm-feuerwehreinsatz-in-wohnpark-in-stendal-4100438",
      "image_url": "https://bmg-images.forward-publishing.io/2025/08/19/3f248382-a2fe-4b60-84c5-944a0939229f.jpeg?rect=0%2C251%2C4000%2C2251&width=100",
      "image_title": "Gasgeruch in einem Wohngebäudekomplex hat für einen größeren Feuerwehreinsatz am Montag, 18. August 2025, an der Arneburger Straße in Stendal gesorgt.",
      "topic": "Sirenengeheul am späten Abend"
    },
    {
      "title": "Verdacht auf Tötungsdelikt in Leipzig: Frau stirbt im Krankenhaus – Zehnjähriger verletzt",
      "url": "https://www.volksstimme.de/blaulicht/polizei-verletzt-tot-mord-taeter-opfer-gewalt-festnahme-4100416",
      "image_url": "https://bmg-images.forward-publishing.io/2025/08/13/285459c6-fd57-4199-adad-1e9154b9caae.jpeg?rect=0%2C0%2C2048%2C1152&width=100",
      "image_title": "Bei einem Großeinsatz hat die Polizei in Leipzig zwei verletzte Menschen gefunden.",
      "topic": "Hintergründe unklar"
    },
    {
      "title": "So schnell war ein Raser auf der B184 in Greppin unterwegs",
      "url": "https://www.volksstimme.de/blaulicht/polizei-blitzer-raser-b184-greppin-bussgeld-fahrverbot-raser-4100408",
      "image_url": "https://bmg-images.forward-publishing.io/2023/05/05/99f828a5-7071-43bc-88fb-4040ee065057.jpeg?rect=0%2C0%2C4000%2C2250&width=100",
      "image_title": "Auf der B184 in Greppin hat die Polizei am Montag die Geschwindigkeit von Autofahrern kontrolliert.",
      "topic": "Bußgeld und Fahrverbot drohen"
    },
    {
      "title": "Fast doppelt so schnell wie erlaubt: Raser auf der L136 in Zschornewitz geblitzt",
      "url": "https://www.volksstimme.de/blaulicht/polizei-raser-l136-zschornewitz-blitzer-geschwindigkeit-bussgeld-fahrverbot-4100400",
      "image_url": "https://bmg-images.forward-publishing.io/2025/03/20/60a71e35-9e9d-4418-a95c-822fe27651f5.jpeg?rect=0%2C10%2C2048%2C1152&width=100",
      "image_title": "Die Polizei hat auf der L136 in Zschornewitz geblitzt.",
      "topic": "Diese Strafen drohen"
    },
    {
      "title": "Tragisches Ende einer Vermisstensuche im Saalekreis: 63-Jährige tot in Bach gefunden",
      "url": "https://www.volksstimme.de/blaulicht/saalekreis-vermisst-frau-tot-bach-polizei-4049033",
      "image_url": "https://bmg-images.forward-publishing.io/2025/05/14/d18b4bfc-fd56-4447-9498-179fbc4748a0.jpeg?rect=103%2C73%2C860%2C484&width=100",
      "image_title": "Die Polizei suchte seit Mai nach einer 63-Jährigen aus dem Saalekreis.",
      "topic": "Monatelang verschwunden"
    },
    {
      "title": "SC Magdeburg gegen TVB Stuttgart am 20. August im Livestream",
      "url": "https://www.volksstimme.de/live/sc-magdeburg-tvb-stuttgart-live-stream-handball-testspiel-hummel-cup-4096333",
      "image_url": "https://bmg-images.forward-publishing.io/2025/08/12/99e7beac-875f-436f-9bb9-63c76cd86e21.jpeg?rect=0%2C0%2C3508%2C1973&width=100",
      "image_title": "Der SC Magdeburg testet am 20. August in der Getec-Arena gegen den Bundesliga-Rivalen TVB Stuttgart. Wir zeigen die Partie im Livestream.",
      "topic": "Handball-Testspiel"
    },
    {
      "title": "Chemnitzer FC gegen 1. FC Magdeburg II am 23. August im Livestream",
      "url": "https://www.volksstimme.de/live/fussball-regionalliga-nordost/chemnitzer-fc-1-fc-magdeburg-live-stream-regionalliga-nordost-4096395",
      "image_url": "https://bmg-images.forward-publishing.io/2025/08/12/da36db21-c7ce-41d6-85c0-30c69be0572e.jpeg?rect=0%2C1%2C3508%2C1973&width=100",
      "image_title": "Der 1. FC Magdeburg II spielt am 23. August beim Chemnitzer FC. Wir zeigen die Partie der Regionalliga Nordost ab 14 Uhr im Livestream.",
      "topic": "Regionalliga Nordost"
    },
    {
      "title": "1. FC Magdeburg II – BFC Dynamo am 27. August im Livestream",
      "url": "https://www.volksstimme.de/live/fussball-regionalliga-nordost/1-fc-magdeburg-bfc-dynamo-live-stream-regionalliga-nordost-27-august-4096425",
      "image_url": "https://bmg-images.forward-publishing.io/2025/08/12/7862dfbd-1ae5-4dbb-bd9c-598452efae3d.jpeg?rect=0%2C1%2C3508%2C1973&width=100",
      "image_title": "Der 1. FC Magdeburg II empfängt am 27. August den BFC Dynamo. Wir zeigen die Partie der Regionalliga Nordost ab 19 Uhr im Livestream.",
      "topic": "Regionalliga Nordost"
    },
    {
      "title": "Stendal verliert Oberliga-Start gegen Plauen - hier gibts die Highlights und das Spiel in voller Länge!",
      "url": "https://www.volksstimme.de/live/livestream-lok-stendal-vfc-plauen-nofv-oberliga-4089524",
      "image_url": "https://bmg-images.forward-publishing.io/2025/07/28/6d7b80c9-723a-4d5a-a235-fca25e2c8229.jpeg?rect=0%2C1%2C3508%2C1973&width=100",
      "image_title": "Zum Saisonauftakt empfing Lok Stendal den VFC Plauen. Bei uns gibts das Spiel noch einmal in voller Länge zu sehen.&nbsp;",
      "topic": "Aufsteiger trifft absteiger"
    },
    {
      "title": "1. FC Magdeburg II unterliegt Halleschen FC im Derby-Kracher - Alle Highlights und Wiederholung",
      "url": "https://www.volksstimme.de/live/fussball-regionalliga-nordost/1-fc-magdeburg-u23-hallescher-fc-derby-live-stream-regionalliga-nordost-wer-uebertraegt-4085932",
      "image_url": "https://bmg-images.forward-publishing.io/2025/07/21/ecf49045-ac31-4ffc-b18c-ddfa24304bb4.jpeg?rect=0%2C1%2C3508%2C1973&width=100",
      "image_title": "Der 1. FC Magdeburg II spielt am 31. Juli gegen den Halleschen FC. Wir zeigen das Sachsen-Anhalt-Derby in der Regionalliga Nordost ab 19 Uhr im Livestream.",
      "topic": "Regionalliga am 31. Juli"
    },
    {
      "title": "FCM-Neuzugang Rayan Ghrieb und sein \"Stürmergefühl\"",
      "url": "https://www.volksstimme.de/sport/1-fc-magdeburg/bei-startelfdebuet-fcm-neuzugang-rayan-ghrieb-ueber-sein-stuermergefuehl-4100033",
      "image_url": "https://bmg-images.forward-publishing.io/2025/08/18/d063db4a-1e92-4ada-a6c0-7b343bb90f9a.jpeg?rect=81%2C208%2C3919%2C2204&width=100",
      "image_title": "Rayan Ghrieb spielt seit Anfang August für den 1. FC Magdeburg. Im zweiten Spiel für den Verein gelang ihm ein Doppelpack.",
      "topic": "Traumhaftes Startelfdebüt"
    },
    {
      "title": "Weniger Chancen, mehr Siege: FCM glänzt mit Effektivität",
      "url": "https://www.volksstimme.de/sport/1-fc-magdeburg/1-fc-magdeburg-effizienz-saarbruecken-dresden-erfolg-guter-start-fiedler-4099295",
      "image_url": "https://bmg-images.forward-publishing.io/2025/08/16/1406f6db-4613-4e6f-a6a0-cb0bef34bbcd.jpeg?rect=0%2C0%2C1000%2C562&width=100",
      "image_title": "Markus Fiedler darf sich über den Einzug in die zweite DFB-Pokalrunde und seinen zweiten Sieg als Magdeburg-Trainer freuen.",
      "topic": "Guter Start für Trainer Fiedler"
    },
    {
      "title": "Rayan Ghrieb wuchtet den 1. FC Magdeburg in die zweite Runde des DFB-Pokals",
      "url": "https://www.volksstimme.de/sport/1-fc-magdeburg/rayan-ghrieb-1-fc-magdeburg-dfb-pokal-1-fc-saarbruecken-matchwinner-4099046",
      "image_url": "https://bmg-images.forward-publishing.io/2025/08/15/3c84f0c5-5bd7-4e0a-9659-83dd182dcf9a.jpeg?rect=341%2C0%2C3124%2C1757&width=100",
      "image_title": "Rayan Ghrieb (rechts) schoss den 1. FC Magdeburg in die zweiten Runde des DFB-Pokals.",
      "topic": "Spektakulär im Saarland"
    },
    {
      "title": "3:8 – JSG Leuna/Wengelsdorf (Flexmodell) erleidet klare Pleite gegen Sportring Mücheln (Flex)",
      "teaser": "Fußball-A-Junioren Landesliga Staffel IV: An diesem Wochenende hat die JSG Leuna/Wengelsdorf (Flexmodell) auf dem eigenen Platz eine bitterliche Niederlage verschmerzen müssen. Gegen den Sportring Mücheln (Flex) unterlag das Team von Ingbert Beier mit 3:8 (2:3).",
      "url": "https://www.volksstimme.de/sport/fussball-landesliga-4-a-sachsen-anhalt/3-8-jsg-leuna-wengelsdorf-flexmodell-erleidet-klare-pleite-gegen-sportring-mucheln-flex-4099598",
      "topic": "Ergebnis 1. Spieltag"
    },
    {
      "title": "SV Merseburg 99 siegt im Heimspiel mit 3:0 gegen SG Döllnitz",
      "teaser": "Am 1. Spieltag der Fußball-A-Junioren Landesliga Staffel IV durfte sich der SV Merseburg 99 vor 37 Fußballfans über einen soliden 3:0 (1:0)-Erfolg gegen die SG Döllnitz freuen.",
      "url": "https://www.volksstimme.de/sport/fussball-landesliga-4-a-sachsen-anhalt/sv-merseburg-99-siegt-im-heimspiel-mit-3-0-gegen-sg-dollnitz-4099683",
      "topic": "Ergebnis 1. Spieltag"
    },
    {
      "title": "10:0 – SV Mertendorf gewinnt haushoch gegen TSV Eintracht Lützen",
      "teaser": "Fußball-A-Junioren Landesliga Staffel IV: Mit einem unfassbaren 10:0 (2:0) fegte die Mannschaft des SV Mertendorf den TSV Eintracht Lützen am Sonntag vom Spielfeld.",
      "url": "https://www.volksstimme.de/sport/fussball-landesliga-4-a-sachsen-anhalt/10-0-sv-mertendorf-gewinnt-haushoch-gegen-tsv-eintracht-lutzen-4099600",
      "topic": "Ergebnis 1. Spieltag"
    },
    {
      "title": "1. FC Zeitz deklassiert SG Langendorf/Zorbau (Flex) mit haushohem 9:1",
      "teaser": "Fußball-A-Junioren Landesliga Staffel IV: Am Wochenende setzte sich der Gastgeber 1. FC Zeitz vor 33 Zuschauern gegen die SG Langendorf/Zorbau (Flex) mit einem überragenden 9:1 (2:0) durch.",
      "url": "https://www.volksstimme.de/sport/fussball-landesliga-4-a-sachsen-anhalt/1-fc-zeitz-deklassiert-sg-langendorf-zorbau-flex-mit-haushohem-9-1-4099596",
      "topic": "Ergebnis 1. Spieltag"
    },
    {
      "title": "Kräftemessen zwischen SV Großgräfendorf und TSG Wörmlitz-Böllberg endet mit Remis 3:3",
      "teaser": "Am 1. Spieltag der Fußball-A-Junioren Landesliga Staffel IV erreichte der Gastgeber SV Großgräfendorf gegen die TSG Wörmlitz-Böllberg ein 3:3 (0:3)-Unentschieden.",
      "url": "https://www.volksstimme.de/sport/fussball-landesliga-4-a-sachsen-anhalt/kraftemessen-zwischen-sv-grossgrafendorf-und-tsg-wormlitz-bollberg-endet-mit-remis-3-3-4099604",
      "topic": "Ergebnis 1. Spieltag"
    },
    {
      "title": "Wackelt nun auch die Ringbrücke an der Sudenburger Wuhne in Magdeburg?",
      "url": "https://www.volksstimme.de/lokal/magdeburg/ringbruecke-pruefung-beton-bahn-verkehrsgefahr-spannbeton-4097761",
      "image_url": "https://bmg-images.forward-publishing.io/2025/08/13/af871ef4-dde9-493e-a059-ec910a8560dd.jpeg?rect=0%2C721%2C4000%2C2250&width=100",
      "image_title": "Die Ringbrücke, die über die Sudenburger Wuhne in Magdeburg führt, wurde anders gebaut als die Bröckel-Brücken.",
      "topic": "Eine Brücke, zwei Bauweisen"
    },
    {
      "title": "Mit Video: Magdeburger Damaschkeplatz plötzlich wieder befahrbar",
      "url": "https://www.volksstimme.de/lokal/magdeburg/damaschkeplatz-baustelle-behelfsbruecke-auto-befahrbar-4093128",
      "image_url": "https://bmg-images.forward-publishing.io/2025/08/05/da5a21a2-19ac-4adc-a066-80e600be5090.jpeg?rect=0%2C0%2C1600%2C900&width=100",
      "image_title": "Am Montag (4. August 2025) wurde der Damaschkeplatz unter den Behelfsbrücken auch für Autos freigegeben.",
      "topic": "Überraschung im Berufsverkehr"
    },
    {
      "title": "So sicher sollen Magdeburgs neue Behelfsbrücken werden",
      "url": "https://www.volksstimme.de/lokal/magdeburg/behelfsbruecke-damaschkeplatz-sicherheit-verkehr-baustelle-4092801",
      "image_url": "https://bmg-images.forward-publishing.io/2025/08/04/c46d2afc-db5c-4817-8f42-efb5a48c7de2.jpeg?rect=0%2C144%2C4000%2C2250&width=100",
      "image_title": "Seit dem 28. Juli ist auch die zweite Behelfsbrücke eingeschoben. Bevor der Damaschkeplatz für den Verkehr freigegeben werden kann, erfolgen noch Anschlussarbeiten an den Magdeburger Ring. Im Zuge dieser werden zusätzliche Maßnahmen zur Erhöhung der Sicherheit vorgenommen.",
      "topic": "Schutz vor Unfällen, Extremwetter, Verschleiß"
    },
    {
      "title": "Provisorischer Übergang über den Magdeburger Ring verschwindet wieder",
      "url": "https://www.volksstimme.de/lokal/magdeburg/magdeburger-ring-baustelle-behelfsbruecke-fussgaenger-4092785",
      "image_url": "https://bmg-images.forward-publishing.io/2025/08/04/e3841b82-61fe-4c84-9e8a-ca71b02e0461.jpeg?rect=0%2C604%2C4000%2C2250&width=100",
      "image_title": "Fortschritt an der Brücken-Baustelle am Damaschkeplatz: Am Montag (4. August 2025) wurde mit dem Rückbau des provisorischen Übergangs über den Magdeburger Ring begonnen.",
      "topic": "Weg am Damaschkeplatz"
    },
    {
      "title": "Wie es am Damaschkeplatz in Magdeburg nun weitergehen soll",
      "url": "https://www.volksstimme.de/lokal/magdeburg/damaschkeplatz-ringbruecke-abriss-behelfsbruecke-magdeburg-4082253",
      "image_url": "https://bmg-images.forward-publishing.io/2025/07/13/34d89a3d-f42d-4019-a5ad-1e6369114fe7.jpeg?rect=0%2C416%2C4000%2C2250&width=100",
      "image_title": "Der Damaschkeplatz in Magdeburg: Nach dem Abriss der maroden Ringbrücke fand am Freitag, den 11. Juli, der Einschub der ersten Behelfsbrücke statt.",
      "topic": "Nach Einschub der ersten Behelfsbrücke"
    },
    {
      "title": "Verband: Viele Politiker setzen auf klimaschädliche Autos",
      "url": "https://www.volksstimme.de/deutschland-und-welt/deutschland/verband-viele-politiker-setzen-auf-klimaschadliche-autos-4100443",
      "image_url": "https://bmg-images.forward-publishing.io/2025/08/19/be3de344-f746-44a3-a0c9-73c07faa8e67.jpeg?rect=0%2C77%2C2048%2C1152&width=100",
      "image_title": "Die Deutsche Umwelthilfe kritisiert seit Jahren, dass viele Spitzenpolitiker bei der Wahl ihrer Dienstwagen nicht auf die Folgen für das Klima achten. (Symbolbild).",
      "topic": "Dienstwagen-Check"
    },
    {
      "title": "Bauern reagieren auf Trockenheit: Mehr Bewässerung und Soja",
      "url": "https://www.volksstimme.de/deutschland-und-welt/wirtschaft/bauern-reagieren-auf-trockenheit-mehr-bewasserung-und-soja-4100413",
      "image_url": "https://bmg-images.forward-publishing.io/2025/08/19/70e0a1fe-e72c-4034-a5df-b39e53abea7a.jpeg?rect=0%2C25%2C2048%2C1152&width=100",
      "image_title": "Nicht einmal fünf Prozent der landwirtschaftlichen Fläche kann bewässert werden.",
      "topic": "Landwirtschaft"
    },
    {
      "title": "Studie: Chinesen drücken Preise für Elektro-Autos",
      "url": "https://www.volksstimme.de/deutschland-und-welt/wirtschaft/studie-chinesen-drucken-preise-fur-elektro-autos-4100370",
      "image_url": "https://bmg-images.forward-publishing.io/2025/08/19/07dade52-92d2-460b-82fe-517a95dc669f.jpeg?rect=0%2C0%2C2048%2C1152&width=100",
      "image_title": "E-Autos für die Welt: Chinas Autobauer fahren voran. (Symbolbild)",
      "topic": "Vor der IAA in München"
    },
    {
      "title": "Rückt Frieden näher? Die Knackpunkte nach dem Ukraine-Gipfel",
      "url": "https://www.volksstimme.de/deutschland-und-welt/politik/ruckt-frieden-naher-die-knackpunkte-nach-dem-ukraine-gipfel-4100351",
      "image_url": "https://bmg-images.forward-publishing.io/2025/08/19/43ee24b3-d110-46ff-9c21-28b3ba9be08f.jpeg?rect=0%2C107%2C2048%2C1152&width=100",
      "image_title": "Trump arbeitet an einem Zweiertreffen Putins mit Selenskyj.",
      "topic": "Russischer Angriffskrieg"
    },
    {
      "title": "Trump will schnelles Zweiertreffen von Putin und Selenskyj",
      "url": "https://www.volksstimme.de/deutschland-und-welt/politik/trump-will-schnelles-zweiertreffen-von-putin-und-selenskyj-4100319",
      "image_url": "https://bmg-images.forward-publishing.io/2025/08/19/b25be9ab-d91a-4e44-b1aa-f14bc886b790.jpeg?rect=0%2C107%2C2048%2C1152&width=100",
      "image_title": "Trump beriet sich mit Selenskyj und europäischen Staats- und Regierungschefs.",
      "topic": "Gipfel in Washington"
    },
    {
      "title": "Ermittlungen gegen Attentäter von Magdeburg abgeschlossen",
      "url": "https://www.volksstimme.de/panorama/ermittlungen-gegen-attentater-von-magdeburg-abgeschlossen-4100441",
      "image_url": "https://bmg-images.forward-publishing.io/2025/08/19/4e086dc1-0685-4be9-97de-7cd6eb8a8483.jpeg?rect=0%2C0%2C2048%2C1152&width=100",
      "image_title": "Die Generalstaatsanwaltschaft hat die Ermittlungen gegen Taleb A. abgeschlossen. (Archivbild)",
      "topic": "Todesfahrt im Dezember"
    },
    {
      "title": "Fünfter Tag im Prozess um Entführung der Block-Kinder",
      "url": "https://www.volksstimme.de/panorama/funfter-tag-im-prozess-um-entfuhrung-der-block-kinder-4100439",
      "image_url": "https://bmg-images.forward-publishing.io/2025/08/19/7dd64928-492c-4398-a187-8d87f5ce6d1e.jpeg?rect=0%2C155%2C2048%2C1152&width=100",
      "image_title": "Die Unternehmerin Christina Block stellt sich als Angeklagte den Fragen des Hamburger Landgerichts.",
      "topic": "Justiz"
    },
    {
      "title": "Sprung aus Fenster: Drei Schwerverletzte bei Brand in Gera",
      "url": "https://www.volksstimme.de/panorama/sprung-aus-fenster-drei-schwerverletzte-bei-brand-in-gera-4100435",
      "image_url": "https://bmg-images.forward-publishing.io/2025/08/19/f2e8a283-11bf-4fb7-a41c-f5fc66bf0ccf.jpeg?rect=0%2C134%2C2048%2C1152&width=100",
      "image_title": "Bei einem Großbrand in einer Altbauwohnung in Gera haben drei Menschen lebensbedrohliche Brandverletzungen erlitten. Einer von ihnen musste sich durch einen Sprung aus dem Fenster retten. (Symbolbild)",
      "topic": "Rettungseinsatz"
    },
    {
      "title": "Frau entdeckt Riesen-Würgeschlange im heimischen Kompost",
      "url": "https://www.volksstimme.de/panorama/frau-entdeckt-riesen-wurgeschlange-im-heimischen-kompost-4100433",
      "image_url": "https://bmg-images.forward-publishing.io/2025/08/19/2012b6e2-efb6-4553-b7a8-7b49d78e1884.jpeg?rect=0%2C592%2C1536%2C864&width=100",
      "image_title": "Wie das Tier in den Garten gelangen konnte, ist noch unklar. (Handout)",
      "topic": "Tierische Gefahr"
    },
    {
      "title": "Kleinkind nach Autounfall in Berlin gestorben",
      "url": "https://www.volksstimme.de/panorama/kleinkind-nach-autounfall-in-berlin-gestorben-4100427",
      "image_url": "https://bmg-images.forward-publishing.io/2025/08/19/995bcfb6-2cce-45bf-920f-cf174e05994d.jpeg?rect=0%2C55%2C2048%2C1152&width=100",
      "image_title": "Am Montag erfasst ein Autofahrer in Berlin-Lichtenberg mit seinem Wagen eine Mutter und ihr Kind – der zweijährige Junge stirbt im Krankenhaus. (Symbolbild)",
      "topic": "Unfälle"
    },
    {
      "title": "Top 10 mit DDR-Klassikern – dieses Gericht ist die Nr. 1 bei Sachsen-Anhalts Kindern",
      "url": "https://www.volksstimme.de/leben/familie/ddr-klassiker-kita-essen-schulessen-sachsen-anhalt-lieblingsgerichte-4100191",
      "image_url": "https://bmg-images.forward-publishing.io/2024/12/27/a2d9b7d8-5fb8-4768-9eb4-ef3afd7deb8b.jpeg?rect=0%2C0%2C1287%2C724&width=100",
      "image_title": "Mittagszeit in der Kita: Viele Kinder in Sachsen-Anhalt bekommen DDR-Klassiker wie Gehacktesstippe oder Milchreis serviert – oft entscheiden aber die Eltern, was bestellt wird",
      "topic": "Essen in Kitas und Schulen"
    },
    {
      "title": "Jugendliche im Sportfieber: Warum Training so beliebt ist – und wann es zu viel wird",
      "url": "https://www.volksstimme.de/leben/familie/jugendliche-fitness-krafttraining-motivation-social-media-gesundheit-sachsen-anhalt-4099903",
      "image_url": "https://bmg-images.forward-publishing.io/2025/08/18/224b2cfd-fb55-4674-9b81-304d3854528a.jpeg?rect=0%2C131%2C4000%2C2250&width=100",
      "image_title": "Mit Hanteln zur Stärke: Auch Mädchen setzen beim Training auf Muskelaufbau.",
      "topic": "Fitness-Hype bei Jugendlichen in Sachsen-Anhalt"
    },
    {
      "title": "So macht Schwimmenlernen Spaß: Kita-Kinder in Halle im XXL-Pool",
      "url": "https://www.volksstimme.de/leben/familie/xxl-pool-schwimmen-lernen-kinder-kita-halle-nichtschwimmer-sachsen-anhalt-drk-schwimmkurs-seepferdchen-abzeichen-4098863",
      "image_url": "https://bmg-images.forward-publishing.io/2025/08/15/c57f493b-ed7b-4cc7-b2d1-6e06876dad54.jpeg?rect=0%2C197%2C3120%2C1755&width=100",
      "image_title": "Wassergewöhnung von klein auf – das bedeutet in einer Kita in Halle mehr als nur Planschen.",
      "topic": "bundesweit einmalig"
    },
    {
      "title": "Die fünf besten Abkühl-Tricks für Familien in Sachsen-Anhalt",
      "url": "https://www.volksstimme.de/leben/familie/sachsen-anhalt-abkuehlung-badeseen-wasserspielplatz-eisdiele-sommerhitze-tropfsteinhoehlen-4099017",
      "image_url": "https://bmg-images.forward-publishing.io/2025/08/15/f27fb93d-d1b4-4300-ba43-eea7bed01d1c.jpeg?rect=0%2C0%2C3840%2C2160&width=100",
      "image_title": "Eisgekühlt bei Sommerhitze: Unter anderem in Wernigerode gibt es eine tolle Eisdiele.",
      "topic": "Sommer-Hitze in Sachsen-Anhalt"
    },
    {
      "title": "Melonen pflücken, Badesee und Kinderfest: Das sind die besten Familien-Ausflüge in Sachsen-Anhalt",
      "url": "https://www.volksstimme.de/leben/familie/kinderfest-ausflugstipps-halle-magdeburg-sachsen-anhalt-familien-kinder-melonen-maislabyrinth-3957666",
      "image_url": "https://bmg-images.forward-publishing.io/2025/08/15/d1e8c753-6711-4ea7-9f69-88dc0d08fc26.jpeg?rect=0%2C209%2C4000%2C2250&width=100",
      "image_title": "Selbst ernten und genießen: Auf einem Hektar wachsen in Zöberitz acht verschiedene Melonensorten, die direkt am Feld gepflückt werden können.",
      "topic": "Abenteuer in Sachsen-Anhalt"
    },
    {
      "title": "Intel bekommt milliardenschwere Investition",
      "url": "https://www.volksstimme.de/leben/technik/intel-bekommt-milliardenschwere-investition-4100362",
      "image_url": "https://bmg-images.forward-publishing.io/2025/08/19/d7afeabd-aba9-4072-bb0f-eae3c3326e60.jpeg?rect=0%2C106%2C2048%2C1152&width=100",
      "image_title": "Intel kann frisches Geld in Milliardenhöhe gut gebrauchen. (Archivbild)",
      "topic": "Kriselnder Chipkonzern"
    },
    {
      "title": "„Gelassene Skepsis“: Tipps für besorgte Gamer-Eltern",
      "url": "https://www.volksstimme.de/leben/gelassene-skepsis-tipps-fur-besorgte-gamer-eltern-4100359",
      "image_url": "https://bmg-images.forward-publishing.io/2025/08/19/c55a5a40-b48d-46bd-8957-f911fb99d5aa.jpeg?rect=0%2C107%2C2048%2C1152&width=100",
      "image_title": "Spiel oder zu real? Gaming kann - ähnlich wie Social Media - positive und negative Effekte im „echten“ Leben haben.",
      "topic": "Neue Studie"
    },
    {
      "title": "Mobbing im Netz: Studie zeigt rauen Umgangston unter Gamern",
      "url": "https://www.volksstimme.de/leben/technik/mobbing-im-netz-studie-zeigt-rauen-umgangston-unter-gamern-4100345",
      "image_url": "https://bmg-images.forward-publishing.io/2025/08/19/6e0a1a29-b46e-4f51-bef5-0da5f9bc72d0.jpeg?rect=0%2C107%2C2048%2C1152&width=100",
      "image_title": "Jung und meist männlich: Besucherinnen und Besucher der Gamescom (Archivbild)",
      "topic": "Vor Gamescom-Start"
    },
    {
      "title": "„Der römische Traum“: „Anno“-Hörspiel startet zur Gamescom",
      "url": "https://www.volksstimme.de/leben/technik/der-romische-traum-anno-horspiel-startet-zur-gamescom-4100308",
      "image_url": "https://bmg-images.forward-publishing.io/2025/08/18/de517b80-7294-4d65-8857-b5a241b5bfdb.jpeg?rect=0%2C0%2C2048%2C1152&width=100",
      "image_title": "Das „Anno“-Hörspiel will ein möglichst breites Publikum in Videospiel-Welten entführen.",
      "topic": "Web- und App-Tipp"
    },
    {
      "title": "Der Nissan Leaf will mit Neuauflage wieder Anschluss finden",
      "url": "https://www.volksstimme.de/leben/auto/der-nissan-leaf-will-mit-neuauflage-wieder-anschluss-finden-4100313",
      "image_url": "https://bmg-images.forward-publishing.io/2025/08/18/ae3d2f84-2e04-43c2-ba90-bdd7c5c0d190.jpeg?rect=0%2C107%2C2048%2C1152&width=100",
      "image_title": "Kein ungeschriebenes Blatt: Der neue Nissan Leaf fährt nun schon in dritter Generation um die Gunst der Kunden.",
      "topic": "Autotest"
    },
    {
      "title": "Das sind die Nominierten für den Deutschen Buchpreis",
      "url": "https://www.volksstimme.de/kultur/das-sind-die-nominierten-fur-den-deutschen-buchpreis-4100442",
      "image_url": "https://bmg-images.forward-publishing.io/2025/08/19/2fd938c7-3ed8-4a2c-abf2-bff5203c64ef.jpeg?rect=0%2C107%2C2048%2C1152&width=100",
      "image_title": "Die Jury hat mehr als 200 Romane für den Deutschen Buchpreis gesichtet. (Symbolbild)",
      "topic": "Preisverdächtige Literatur"
    },
    {
      "title": "Sharon Stone über Comeback: „Möchte etwas hinterlassen“",
      "url": "https://www.volksstimme.de/kultur/tv-und-streaming/sharon-stone-uber-comeback-mochte-etwas-hinterlassen-4100410",
      "image_url": "https://bmg-images.forward-publishing.io/2025/08/19/dc870559-24c3-4786-99da-fa2944b5eb03.jpeg?rect=0%2C107%2C2048%2C1152&width=100",
      "image_title": "Sharon Stone ist ab dieser Woche in dem Action-Streifen „Nobody 2“ zu sehen. (Archivbild)",
      "topic": "Leute"
    },
    {
      "title": "Kriegsende: Das verschollene Tagebuch des Will Quadflieg",
      "url": "https://www.volksstimme.de/kultur/buch/kriegsende-das-verschollene-tagebuch-des-will-quadflieg-4100389",
      "image_url": "https://bmg-images.forward-publishing.io/2025/08/19/bc57d65b-d951-42d1-8acc-66aa5a1e9b53.jpeg?rect=0%2C111%2C2048%2C1152&width=100",
      "image_title": "Will Quadflieg hatte nach dem Zweiten Weltkrieg eine große Schauspielkarriere - doch deren Anfänge lagen in der NS-Zeit. (Archivbild).",
      "topic": "Entdeckt von der Tochter"
    },
    {
      "title": "Ochsenknecht fliegt bei Reality-Show raus: „Bin happy“",
      "url": "https://www.volksstimme.de/kultur/tv-und-streaming/ochsenknecht-fliegt-bei-reality-show-raus-bin-happy-4100381",
      "image_url": "https://bmg-images.forward-publishing.io/2025/08/19/7d206d60-6806-4c8a-8c04-c18b3489c339.jpeg?rect=0%2C177%2C2048%2C1152&width=100",
      "image_title": "Der Schauspieler war im Juni in Hamburg wegen einer nicht gezahlten Hotelrechnung festgenommen worden. (Archivbild)",
      "topic": "Vor Gerichtstermin"
    },
    {
      "title": "Aktenzeichen XY: Diese fünf Verbrechen sollen am Mittwoch aufgeklärt werden",
      "url": "https://www.volksstimme.de/kultur/tv-und-streaming/zdf-aktenzeichen-xy-naechste-folge-august-verbrechen-krimi-4093485",
      "image_url": "https://bmg-images.forward-publishing.io/2025/08/06/8ee80f6a-db7b-41b1-8571-95255fed3238.jpeg?rect=222%2C333%2C3556%2C2000&width=100",
      "image_title": "Im August sollen bei der ZDF-Sendung „Aktenzeichen XY … ungelöst“ fünf Verbrechen aufgelöst werden.",
      "topic": "Verfolgung, Raub und Geiselnahme"
    }
  ]
}