{
  "timestamp": "2025-02-14T04:11:14",
  "url": "https://www.compact-online.de/compact-aktuell/",
  "response": {
    "status": 200
  },
  "scripts": [
    {
      "type": "text/javascript",
      "src": "https://www.compact-online.de/wp-content/745ee08d9d758eabc6c2ee68b61ff861/dist/2100398172.js?ver=af932e55e5f194c31fb69933f509c364",
      "id": "real-cookie-banner-pro-vendor-real-cookie-banner-pro-banner-js",
      "text": null
    },
    {
      "type": "text/javascript",
      "src": "https://www.compact-online.de/wp-content/745ee08d9d758eabc6c2ee68b61ff861/dist/696531927.js?ver=20a2d060ef6d431d1f57b5de6cffda69",
      "id": "real-cookie-banner-pro-banner-js",
      "text": null
    },
    {
      "type": "text/javascript",
      "src": "https://www.compact-online.de/wp-includes/js/jquery/jquery.min.js?ver=3.7.1",
      "id": "jquery-core-js",
      "text": null
    },
    {
      "type": "text/javascript",
      "src": "https://www.compact-online.de/wp-includes/js/jquery/jquery-migrate.min.js?ver=3.4.1",
      "id": "jquery-migrate-js",
      "text": null
    },
    {
      "type": "text/javascript",
      "src": "https://www.compact-online.de/wp-content/uploads/712/354/public/assets/js/839.js?ver=1.56.1",
      "id": "advanced-ads-advanced-js-js",
      "text": null
    },
    {
      "type": "text/javascript",
      "src": "https://www.compact-online.de/wp-content/plugins/elementor/assets/lib/font-awesome/js/v4-shims.min.js?ver=3.24.7",
      "id": "font-awesome-4-shim-js",
      "text": null
    },
    {
      "type": "text/javascript",
      "src": "https://www.compact-online.de/wp-content/plugins/advanced-ads/admin/assets/js/advertisement.js?ver=1.56.1",
      "id": "advanced-ads-find-adblocker-js",
      "text": null
    },
    {
      "type": "text/javascript",
      "src": "https://www.compact-online.de/wp-content/745ee08d9d758eabc6c2ee68b61ff861/dist/202597715.js?ver=684df420d0ee25a796454c9c4204794c",
      "id": "real-cookie-banner-pro-blocker-js",
      "text": null
    },
    {
      "type": "text/javascript",
      "src": "https://www.compact-online.de/wp-content/themes/smart-mag/js/lazyload.js?ver=10.2.1",
      "id": "smartmag-lazyload-js",
      "text": null
    },
    {
      "type": "text/javascript",
      "src": "https://www.compact-online.de/wp-content/plugins/download-monitor/assets/js/dlm-xhr.min.js?ver=5.0.21",
      "id": "dlm-xhr-js",
      "text": null
    },
    {
      "type": "text/javascript",
      "src": "https://www.compact-online.de/wp-includes/js/jquery/ui/core.min.js?ver=1.13.3",
      "id": "jquery-ui-core-js",
      "text": null
    },
    {
      "type": "text/javascript",
      "src": "https://www.compact-online.de/wp-content/plugins/qi-addons-for-elementor/assets/js/main.min.js?ver=1.8.1",
      "id": "qi-addons-for-elementor-script-js",
      "text": null
    },
    {
      "type": "text/javascript",
      "src": "https://www.compact-online.de/wp-content/themes/smart-mag/js/jquery.mfp-lightbox.js?ver=10.2.1",
      "id": "magnific-popup-js",
      "text": null
    },
    {
      "type": "text/javascript",
      "src": "https://www.compact-online.de/wp-content/themes/smart-mag/js/jquery.sticky-sidebar.js?ver=10.2.1",
      "id": "theia-sticky-sidebar-js",
      "text": null
    },
    {
      "type": "text/javascript",
      "src": "https://www.compact-online.de/wp-content/themes/smart-mag/js/theme.js?ver=10.2.1",
      "id": "smartmag-theme-js",
      "text": null
    },
    {
      "type": "text/javascript",
      "src": "https://www.compact-online.de/wp-content/plugins/elementor/assets/js/webpack.runtime.min.js?ver=3.24.7",
      "id": "elementor-webpack-runtime-js",
      "text": null
    },
    {
      "type": "text/javascript",
      "src": "https://www.compact-online.de/wp-content/plugins/elementor/assets/js/frontend-modules.min.js?ver=3.24.7",
      "id": "elementor-frontend-modules-js",
      "text": null
    },
    {
      "type": "text/javascript",
      "src": "https://www.compact-online.de/wp-content/plugins/elementor/assets/js/frontend.min.js?ver=3.24.7",
      "id": "elementor-frontend-js",
      "text": null
    },
    {
      "type": "text/javascript",
      "src": "https://www.compact-online.de/wp-includes/js/dist/hooks.min.js?ver=2810c76e705dd1a53b18",
      "id": "wp-hooks-js",
      "text": null
    },
    {
      "type": "text/javascript",
      "src": "https://www.compact-online.de/wp-includes/js/dist/i18n.min.js?ver=5e580eb46a90c2b997e6",
      "id": "wp-i18n-js",
      "text": null
    },
    {
      "type": "text/javascript",
      "src": "https://www.compact-online.de/wp-content/plugins/qi-addons-for-elementor/inc/plugins/elementor/assets/js/elementor.js?ver=6.6.2",
      "id": "qi-addons-for-elementor-elementor-js",
      "text": null
    },
    {
      "type": "text/javascript",
      "src": "https://www.compact-online.de/wp-content/plugins/pro-elements/assets/js/webpack-pro.runtime.min.js?ver=3.24.4",
      "id": "elementor-pro-webpack-runtime-js",
      "text": null
    },
    {
      "type": "text/javascript",
      "src": "https://www.compact-online.de/wp-content/plugins/pro-elements/assets/js/frontend.min.js?ver=3.24.4",
      "id": "elementor-pro-frontend-js",
      "text": null
    },
    {
      "type": "text/javascript",
      "src": "https://www.compact-online.de/wp-content/plugins/pro-elements/assets/js/elements-handlers.min.js?ver=3.24.4",
      "id": "pro-elements-handlers-js",
      "text": null
    }
  ],
  "articles": [
    {
      "title": "Frieden mit Russland? Thomas Röper ordnet ein",
      "teaser": "Das Telefonat zwischen Putin und Trump versetzt die Welt in Aufruhe! Die einen hoffen auf…"
    },
    {
      "title": "Durchbruch! Trump und Putin wollen Frieden machen",
      "teaser": "Endlich! Der Frieden in der Ukraine ist in greifbare Nähe gerückt. Das ist es, wonach…"
    },
    {
      "title": "Patriotische Allianz: Weidel und Orban im O-Ton",
      "teaser": "Im Rahmen ihres Besuchs bei Ungarns Ministerpräsident Viktor Orban in Budapest trat AfD-Kanzlerkandidatin Alice Weidel…"
    },
    {
      "title": "Auto-Anschlag! Asylant rast in Menschenmenge!",
      "teaser": "27 Verletzte bei Auto-Anschlag in München! Ein Kind schwebt in Lebensgefahr. Der Amok-Fahrer: Ein straffälliger…"
    },
    {
      "title": "Drei Tage im Leben des Olaf S.COMPACT+",
      "teaser": "Dieser Artikel erschien im neuen COMPACT-Spezial 43: „Die Altparteien. Wie sie uns belügen“. Der Verrat…"
    },
    {
      "title": "Deep State zittert: Tulsi Gabbard bestätigt",
      "teaser": "Der nächste Schlag gegen den Tiefen Staat: Die Kriegsgegnerin und Antiimperialistin Tulsi Gabbard wurde vom…"
    },
    {
      "title": "80 Jahre Bombenterror: Wir gedenken der Opfer",
      "teaser": "Am 13./14. Februar 1945 versank die mit Flüchtlingen aus dem Osten überfüllte Barockstadt Dresden im…"
    },
    {
      "title": "Täter Afghane: Auto-Anschlag auf Verdi-Demo in München!",
      "teaser": "Gegen 10.30 Uhr hat es am Donnerstagvormittag den nächsten Terroranschlag in Deutschland gegeben. Ein 24-jähriger…"
    },
    {
      "title": "Ukraine: Trump und Putin vereinbaren Friedensgipfel",
      "teaser": "Schock für die Kriegstreiber: US-Präsident Donald Trump und sein russischer Amtskollege Wladimir Putin haben sich…"
    },
    {
      "title": "Weidel punktet international",
      "teaser": "Zitat des Tages: „Dass Weidel mitten im Bundestagswahlkampf auf internationaler Bühne derart punkten kann, hat…"
    },
    {
      "title": "False Flag? Der mysteriöse AfD-Drohbrief",
      "teaser": "„Staatsschutz ermittelt nach Drohbrief an schwulen Propst“, titelt der Spiegel reißerisch und berichtet wie zahlreiche…"
    },
    {
      "title": "Hart, aber herzlich: Das germanische Recht",
      "teaser": "Die Rechtskulturen der Römer und Germanen waren so unterschiedlich wie ihre Gesellschaften selbst. Erst…"
    },
    {
      "title": "Lebenswichtiges Hormon – Fluch und Segen zugleich",
      "teaser": "Dieses Hormon wird oft als grundsätzlich schlecht betrachtet. Es hat aber auch lebenswichtige Funktionen. Wenn…"
    },
    {
      "title": "Erdbeben: Weidel und Orban schmieden Allianz!",
      "teaser": "Wichtiger Erfolg für ein Europa der freien Völker: Viktor Orbán hatte es bislang nie so…"
    },
    {
      "title": "Dresden: Antifa will „Flamme der Erinnerung“ blockieren",
      "teaser": "Zum 80. Jahrestag der alliierten Terrorangriffe auf Dresden finden zahlreiche Gedenkaktionen statt. Auch die „Flamme…"
    },
    {
      "title": "Österreich: Blau-Schwarz gescheitert",
      "teaser": "Ende, Aus: FPÖ-Chef Herbert Kickl hat soeben das Scheitern der Koalitionsverhandlungen mit der ÖVP verkündet.…"
    },
    {
      "title": "Alliierter Bombenterror: Die wichtigsten Quellen",
      "teaser": "Die Luftangriffe gegen deutsche Städte folgte von Anfang an der Vernichtungslogik Churchills. Wir nennen die wichtigsten Quellen."
    },
    {
      "title": "Titus und TarantulaCOMPACT+",
      "teaser": "Dieser Artikel erschien im COMPACT-Spezial 27: “Geheimakte Kinderschänder. Die Netzwerke des Bösen”. Die Clintons: Spinnen…"
    },
    {
      "title": "FBI-Geheimplan gegen die AfD: Gescheitert!",
      "teaser": "Seit einigen Tagen weisen unsere Kollegen von AUF1 auf eine drohende False-Flag-Aktion des FBI gegen…"
    },
    {
      "title": "Roland Kaiser: Für Gendern, gegen AfD",
      "teaser": "Schlagerstar Roland Kaiser ist vom „woke mind virus“ (Elon Musk) infiziert: In einem aktuellen Interview…"
    },
    {
      "title": "Baerbock: Keine Kanzlerin wegen Russland?",
      "teaser": "Zitat des Tages: „Dass sie 2021 trotz starken Rückenwinds nicht den Wahlsieg für die Grünen…"
    },
    {
      "title": "Zu wenig Reichweite: Habeck wittert Zensur",
      "teaser": "Die Beiträge der Grünen erfreuen sich derzeit in sozialen Netzwerken keiner allzu hohen Beliebtheit. Ein…"
    },
    {
      "title": "Nächster Geldregen: AfD erbt fast 6 Millionen Euro",
      "teaser": "Für die AfD läuft es derzeit finanziell bestens: Nachdem in den letzten Wochen mehrere Millionenspenden…"
    },
    {
      "title": "Habeck-Aus: Putsch-Plan enthüllt!",
      "teaser": "Robert Habeck ist scheinbar kurz vor dem Wahltag am Ende. Der Vizekanzler muss sich nicht…"
    },
    {
      "title": "Drei Jahre Knast für Kritik am Migrations-Pakt?!",
      "teaser": "Prag: Dem tschechischen Oppositionschef Tomio Okamura drohen drei Jahre Haft, weil er den EU-Migrationspakt kritisiert…"
    },
    {
      "title": "Dresden: Linke Hetze gegen Gedenken",
      "teaser": "Am Donnerstag jährt sich die Vernichtung Dresdens durch anglo-amerikanische Bomberflotten zum 80. Mal. Während viele…"
    },
    {
      "title": "Der gute Geist von RibbeckCOMPACT+",
      "teaser": "Neu gelesen: Theodor Fontane. Zum 200. Jubiläum feiert man Theodor Fontane als Klassiker realistischer Frauen-…"
    },
    {
      "title": "Neue Umfrage: Linke drin, BSW raus",
      "teaser": "Anderthalb Wochen vor der Bundestagswahl ist das Rennen entlang der Fünf-Prozent-Hürde so spannend, wie lange…"
    },
    {
      "title": "24 Jahre Haft drohen: Antifa „Maja“ vor Gericht",
      "teaser": "Das Bundesverfassungsgericht hat zwar kürzlich entschieden, dass die Auslieferung des Linksextremisten Simeon Ravi T., der…"
    },
    {
      "title": "Gaza: Waffenruhe droht zu scheitern",
      "teaser": "Die seit Mitte Januar pausierenden Kämpfe in Gaza könnten in Kürze wieder aufgenommen werden, eine…"
    }
  ]
}